<?xml version="1.0" encoding="utf-8"?><ArrayOfProduct xmlns:xsi="http://www.w3.org/2001/XMLSchema-instance" xmlns:xsd="http://www.w3.org/2001/XMLSchema"><Product><Id>376326</Id><Name>product1</Name><Price>805</Price><Category>StringInstrument</Category><InStock>0</InStock></Product><Product><Id>412789</Id><Name>product3</Name><Price>559</Price><Category>KeyBoard</Category><InStock>9</InStock></Product><Product><Id>533228</Id><Name>product4</Name><Price>643</Price><Category>BowInstrument</Category><InStock>12</InStock></Product><Product><Id>222807</Id><Name>product5</Name><Price>347</Price><Category>Percussions</Category><InStock>15</InStock></Product><Product><Id>903884</Id><Name>product6</Name><Price>1099</Price><Category>StringInstrument</Category><InStock>18</InStock></Product><Product><Id>613085</Id><Name>product9</Name><Price>1948</Price><Category>BowInstrument</Category><InStock>27</InStock></Product><Product><Id>200688</Id><Name>product10</Name><Price>1903</Price><Category>Percussions</Category><InStock>30</InStock></Product><Product><Id>111112</Id><Name>stam2</Name><Price>110</Price><Category>KeyBoard</Category><InStock>51</InStock></Product><Product><Id>111116</Id><Name>stam6</Name><Price>541</Price><Category>WindInstrument</Category><InStock>56</InStock></Product><Product><Id>111113</Id><Name>stam3</Name><Price>111</Price><Category>KeyBoard</Category><InStock>48</InStock></Product><Product><Id>111111</Id><Name>stam</Name><Price>100</Price><Category>KeyBoard</Category><InStock>49</InStock></Product><Product><Id>686995</Id><Name>product7</Name><Price>100</Price><Category>WindInstrument</Category><InStock>21</InStock></Product><Product><Id>111115</Id><Name>wsedf</Name><Price>541</Price><Category>WindInstrument</Category><InStock>55</InStock></Product><Product><Id>754334</Id><Name>qqqq</Name><Price>354</Price><Category>WindInstrument</Category><InStock>34</InStock></Product><Product><Id>111114</Id><Name>stam4</Name><Price>141</Price><Category>WindInstrument</Category><InStock>53</InStock></Product><Product><Id>668534</Id><Name>product2</Name><Price>1267</Price><Category>WindInstrument</Category><InStock>6</InStock></Product><Product><Id>110306</Id><Name>product8</Name><Price>1198</Price><Category>KeyBoard</Category><InStock>24</InStock></Product></ArrayOfProduct>